lambda_cache/__init__.py
lambda_cache/caching_logic.py
lambda_cache/exceptions.py
lambda_cache/s3.py
lambda_cache/secrets_manager.py
lambda_cache/ssm.py
lambda_cache-0.8.1.dist-info/LICENSE
lambda_cache-0.8.1.dist-info/WHEEL
lambda_cache-0.8.1.dist-info/METADATA
lambda_cache-0.8.1.dist-info/RECORD
