Metadata-Version: 2.1
Name: lambda-cache
Version: 0.8.1
Summary: Python utility for simple caching in AWS Lambda functions
Home-page: https://github.com/keithrozario/lambda-cache
License: MIT
Keywords: aws,aws_parameter_store,aws_lambda,cache
Author: keithrozario
Author-email: keith@keithrozario.com
Requires-Python: >=3.6.1,<4.0.0
Classifier: Development Status :: 4 - Beta
Classifier: Intended Audience :: Developers
Classifier: License :: OSI Approved :: MIT License
Classifier: Natural Language :: English
Classifier: Programming Language :: Python :: 3
Classifier: Programming Language :: Python :: 3.6
Classifier: Programming Language :: Python :: 3.7
Classifier: Programming Language :: Python :: 3.8
Project-URL: Bug Tracker, https://github.com/keithrozario/lambda_cache/issues
Project-URL: Documentation, https://lambda-cache.readthedocs.io/en/latest/
Project-URL: Docs, https://lambda-cache.readthedocs.io
Project-URL: Repository, https://github.com/keithrozario/lambda-cache
